app/__init__.py
app/config.py
app/models.py
app/views.py
flask_starter_cli-0.1.0.dist-info/METADATA
flask_starter_cli-0.1.0.dist-info/WHEEL
flask_starter_cli-0.1.0.dist-info/entry_points.txt
flask_starter_cli-0.1.0.dist-info/top_level.txt
flask_starter_cli-0.1.0.dist-info/RECORD
