Metadata-Version: 2.2
Name: flask-starter-cli
Version: 0.1.0
Summary: A Flask CLI tool for generating starter templates
Home-page: https://github.com/lyznne/flask-blog-starter.git
Author: lyznne
Author-email: emuthiani26@gmail.com
Classifier: Programming Language :: Python :: 3
Classifier: License :: OSI Approved :: MIT License
Classifier: Operating System :: OS Independent
Requires-Python: >=3.7
Requires-Dist: Flask
Requires-Dist: click
Dynamic: author
Dynamic: author-email
Dynamic: classifier
Dynamic: description
Dynamic: description-content-type
Dynamic: home-page
Dynamic: requires-dist
Dynamic: requires-python
Dynamic: summary
